helpers/__init__.py
helpers/api.py
helpers/shortcuts.py
helpers/contrib/__init__.py
helpers/contrib/download_decam_expnum.py
helpers/contrib/exposure_map.py
helpers/contrib/exposure_map_v2.py
helpers/contrib/night_files.py
wrap_astro_api-0.0.1.dist-info/LICENSE
wrap_astro_api-0.0.1.dist-info/METADATA
wrap_astro_api-0.0.1.dist-info/WHEEL
wrap_astro_api-0.0.1.dist-info/top_level.txt
wrap_astro_api-0.0.1.dist-info/RECORD
