Metadata-Version: 2.1
Name: wrap-astro-api
Version: 0.0.1
Summary: Python wrapper for Astro Archive web API
Home-page: https://github.com/pypa/sampleproject
Author: S. Pothier
Author-email: pothier@noao.edu
License: UNKNOWN
Platform: UNKNOWN
Classifier: Programming Language :: Python :: 3
Classifier: License :: OSI Approved :: MIT License
Classifier: Operating System :: OS Independent
Requires-Python: >=3.6
